odoo/addons/l10n_ro_payment_to_statement/README.rst
odoo/addons/l10n_ro_payment_to_statement/__init__.py
odoo/addons/l10n_ro_payment_to_statement/__manifest__.py
odoo/addons/l10n_ro_payment_to_statement/i18n/l10n_ro_payment_to_statement.pot
odoo/addons/l10n_ro_payment_to_statement/i18n/ro.po
odoo/addons/l10n_ro_payment_to_statement/models/__init__.py
odoo/addons/l10n_ro_payment_to_statement/models/account_bank_statement.py
odoo/addons/l10n_ro_payment_to_statement/models/account_journal.py
odoo/addons/l10n_ro_payment_to_statement/models/account_move.py
odoo/addons/l10n_ro_payment_to_statement/models/account_payment.py
odoo/addons/l10n_ro_payment_to_statement/readme/DESCRIPTION.md
odoo/addons/l10n_ro_payment_to_statement/security/ir.model.access.csv
odoo/addons/l10n_ro_payment_to_statement/static/description/icon.png
odoo/addons/l10n_ro_payment_to_statement/static/description/icon.svg
odoo/addons/l10n_ro_payment_to_statement/static/description/index.html
odoo/addons/l10n_ro_payment_to_statement/tests/__init__.py
odoo/addons/l10n_ro_payment_to_statement/tests/common.py
odoo/addons/l10n_ro_payment_to_statement/tests/test_account_bank_statement.py
odoo/addons/l10n_ro_payment_to_statement/tests/test_account_journal.py
odoo/addons/l10n_ro_payment_to_statement/tests/test_account_move.py
odoo/addons/l10n_ro_payment_to_statement/tests/test_payment.py
odoo/addons/l10n_ro_payment_to_statement/views/account_journal_dashboard_view.xml
odoo/addons/l10n_ro_payment_to_statement/views/account_journal_view.xml
odoo/addons/l10n_ro_payment_to_statement/views/account_payment_view.xml
odoo_addon_l10n_ro_payment_to_statement-19.0.1.1.0.dist-info/METADATA
odoo_addon_l10n_ro_payment_to_statement-19.0.1.1.0.dist-info/WHEEL
odoo_addon_l10n_ro_payment_to_statement-19.0.1.1.0.dist-info/top_level.txt
odoo_addon_l10n_ro_payment_to_statement-19.0.1.1.0.dist-info/RECORD
